keg_elements/.gitignore
keg_elements/__init__.py
keg_elements/conftest.py
keg_elements/core.py
keg_elements/crypto.py
keg_elements/decorators.py
keg_elements/encoding.py
keg_elements/extensions.py
keg_elements/http.py
keg_elements/sentry.py
keg_elements/testing.py
keg_elements/version.py
keg_elements/views.py
keg_elements/db/__init__.py
keg_elements/db/columns.py
keg_elements/db/migrations.py
keg_elements/db/mixins.py
keg_elements/db/utils.py
keg_elements/forms/__init__.py
keg_elements/forms/state_field.py
keg_elements/forms/validators.py
keg_elements/i18n/babel.cfg
keg_elements/i18n/keg_elements.pot
keg_elements/i18n/es/LC_MESSAGES/keg_elements.mo
keg_elements/i18n/es/LC_MESSAGES/keg_elements.po
keg_elements/templates/keg-elements/form-view.html
keg_elements/templates/keg-elements/grid-view.html
keg_elements/templates/keg-elements/forms/datetime-helper.js
keg_elements/templates/keg-elements/forms/horizontal-b3.html
keg_elements/templates/keg-elements/forms/horizontal-b4.html
keg_elements/templates/keg-elements/forms/horizontal-static.html
keg_elements/templates/keg-elements/forms/select2-scripts.html
keg_elements/templates/keg-elements/forms/select2-styles.html
keg_elements/tests/__init__.py
keg_elements/tests/test_columns.py
keg_elements/tests/test_crypto.py
keg_elements/tests/test_db_migrations.py
keg_elements/tests/test_db_mixins.py
keg_elements/tests/test_db_utils.py
keg_elements/tests/test_decorators.py
keg_elements/tests/test_encoding.py
keg_elements/tests/test_sentry.py
keg_elements/tests/test_templates.py
keg_elements/tests/test_testing.py
keg_elements/tests/test_forms/__init__.py
keg_elements/tests/test_forms/test_form.py
keg_elements/tests/test_forms/test_state_field.py
keg_elements/tests/test_forms/test_validators.py
keg_elements/tests/test_views/__init__.py
keg_elements/tests/test_views/test_views.py
kegel_app/__init__.py
kegel_app/app.py
kegel_app/cli.py
kegel_app/config.py
kegel_app/extensions.py
kegel_app/forms.py
kegel_app/grids.py
KegElements-0.12.1.dist-info/METADATA
KegElements-0.12.1.dist-info/WHEEL
KegElements-0.12.1.dist-info/top_level.txt
KegElements-0.12.1.dist-info/RECORD
