Metadata-Version: 2.1
Name: KegElements
Version: 0.12.1
Summary: A testing ground for Keg related code and ideas.
Home-page: https://github.com/level12/keg-elements
Author: Randy Syring
Author-email: randy.syring@level12.io
License: BSD
Platform: UNKNOWN
Classifier: Intended Audience :: Developers
Classifier: License :: OSI Approved :: BSD License
Classifier: Operating System :: OS Independent
Classifier: Programming Language :: Python :: 3
Classifier: Programming Language :: Python :: 3.7
Classifier: Programming Language :: Python :: 3.8
Classifier: Programming Language :: Python :: 3.9
Classifier: Programming Language :: Python :: 3.10
Requires-Dist: arrow
Requires-Dist: Flask-WTF
Requires-Dist: Keg (>=0.11.0)
Requires-Dist: pytz
Requires-Dist: WTForms-Alchemy (>=0.18.0)
Requires-Dist: wtforms (>=3.1.0)
Requires-Dist: cryptography
Requires-Dist: sentry-sdk (>=2)
Provides-Extra: i18n
Requires-Dist: morphi ; extra == 'i18n'
Provides-Extra: tests
Requires-Dist: alembic ; extra == 'tests'
Requires-Dist: flask-webtest ; extra == 'tests'
Requires-Dist: pre-commit ; extra == 'tests'
Requires-Dist: psycopg2-binary ; extra == 'tests'
Requires-Dist: pyquery ; extra == 'tests'
Requires-Dist: pytest ; extra == 'tests'
Requires-Dist: pytest-cov ; extra == 'tests'
Requires-Dist: pyodbc ; extra == 'tests'
Requires-Dist: responses ; extra == 'tests'
Requires-Dist: sqlalchemy-pyodbc-mssql ; extra == 'tests'
Requires-Dist: tox ; extra == 'tests'
Requires-Dist: freezegun ; extra == 'tests'
Requires-Dist: webgrid ; extra == 'tests'
Requires-Dist: xlsxwriter ; extra == 'tests'
